Workbook

Sheet Cover
A1: HUL Valuation — DCF MODEL
A2: HINDUSTAN UNILEVER LIMITED
A4: NSE: HINDUNILVR | Sector: FMCG — Personal & Household Products | Index: Nifty 50
A6: Model Contents
A7: 1. Assumptions
A8: 2. Income Statement
A9: 3. Balance Sheet
A10: 4. Cash Flow Statement
A11: 5. Discounted Cash Flow (DCF)
A12: 6. Sensitivity Analysis
A15: Note: Historical figures (FY2023, FY2024) are approximate public-domain figures (Screener / Annual Report) for illustrative/practice purposes. Verify against the latest Annual Report before relying on this for submission.

Sheet Assumptions
A1: ASSUMPTIONS
A4: Line Item | B4: FY2023 | C4: FY2024 | D4: FY2025E | E4: FY2026E | F4: FY2027E | G4: FY2028E | H4: FY2029E | I4: Source / Note
A5: Revenue Growth % | C5: 0.0437 | D5: 0.08 | E5: 0.09 | F5: 0.09 | G5: 0.085 | H5: 0.08 | I5: FY24 actual ~4.4%; FY25E-29E assumed step-up then maturity
A6: EBITDA Margin % | B6: 0.23 | C6: 0.24 | D6: 0.245 | E6: 0.25 | F6: 0.25 | G6: 0.25 | H6: 0.25 | I6: Source: Screener/Annual Report (approx). Verify exact figures.
A7: Tax Rate % | B7: 0.255 | C7: 0.253 | D7: 0.252 | E7: 0.252 | F7: 0.252 | G7: 0.252 | H7: 0.252 | I7: Effective tax rate, post new corporate tax regime (~25.2%)
A8: D&A (₹ Cr) | B8: 980 | C8: 1020 | D8: 1080 | E8: 1140 | F8: 1200 | G8: 1260 | H8: 1320 | I8: Tracks capex growth ~5-6%/yr
A9: Capex (₹ Cr) | B9: 1100 | C9: 1180 | D9: 1300 | E9: 1400 | F9: 1500 | G9: 1600 | H9: 1700 | I9: ~2% of revenue, asset-light FMCG model
A11: Working Capital Assumptions (FMCG typically has negative working capital)
A12: DSO (Debtor Days) | B12: 15 | C12: 15 | D12: 15 | E12: 14 | F12: 14 | G12: 14 | H12: 14
A13: DIO (Inventory Days) | B13: 60 | C13: 58 | D13: 58 | E13: 57 | F13: 56 | G13: 55 | H13: 55
A14: DPO (Payable Days) | B14: 90 | C14: 92 | D14: 93 | E14: 94 | F14: 95 | G14: 95 | H14: 95 | I14: COGS proxy used for Inventory/Payable days = Revenue x (1-EBITDA Margin)
A16: Capital Structure & Debt Schedule
A17: Opening Debt (₹ Cr) | B17: 2200 | C17: =B19 -> 2200 | D17: =C19 -> 2250 | E17: =D19 -> 2250 | F17: =E19 -> 2250 | G17: =F19 -> 2250 | H17: =G19 -> 2250
A18: Change in Debt (₹ Cr) | C18: 50 | D18: 0 | E18: 0 | F18: 0 | G18: 0 | H18: 0
A19: Closing Debt (₹ Cr) | B19: =B17+B18 -> 2200 | C19: =C17+C18 -> 2250 | D19: =D17+D18 -> 2250 | E19: =E17+E18 -> 2250 | F19: =F17+F18 -> 2250 | G19: =G17+G18 -> 2250 | H19: =H17+H18 -> 2250
A20: Cost of Debt % | B20: 0.065 | C20: 0.065 | D20: 0.065 | E20: 0.065 | F20: 0.065 | G20: 0.065 | H20: 0.065
A21: Interest Expense (₹ Cr) | B21: 90 | C21: =AVERAGE(C17:C19)*C20 -> 97.5 | D21: =AVERAGE(D17:D19)*D20 -> 97.5 | E21: =AVERAGE(E17:E19)*E20 -> 97.5 | F21: =AVERAGE(F17:F19)*F20 -> 97.5 | G21: =AVERAGE(G17:G19)*G20 -> 97.5 | H21: =AVERAGE(H17:H19)*H20 -> 97.5 | I21: Formula: Average(Opening,Closing Debt) x Cost of Debt. FY23 hardcoded actual.
A23: Dividend Policy
A24: Dividend Payout % | B24: 0.95 | C24: 0.95 | D24: 0.9 | E24: 0.9 | F24: 0.9 | G24: 0.9 | H24: 0.9 | I24: HUL historically pays out ~90-100% of net income

Sheet Income Statement
A1: INCOME STATEMENT
A2: HINDUSTAN UNILEVER LIMITED (₹ in Crores)
A4: Line Item | B4: FY2023 | C4: FY2024 | D4: FY2025E | E4: FY2026E | F4: FY2027E | G4: FY2028E | H4: FY2029E | I4: Formula / Source
A5: Revenue | B5: 58154 | C5: =B5*(1+Assumptions!C5) -> 60695.33 | D5: =C5*(1+Assumptions!D5) -> 65550.956 | E5: =D5*(1+Assumptions!E5) -> 71450.542 | F5: =E5*(1+Assumptions!F5) -> 77881.091 | G5: =F5*(1+Assumptions!G5) -> 84500.984 | H5: =G5*(1+Assumptions!H5) -> 91261.062 | I5: FY2023 actual (anchor year) — Source: Screener/Annual Report
A6: EBITDA | B6: =B5*Assumptions!B6 -> 13375.42 | C6: =C5*Assumptions!C6 -> 14566.879 | D6: =D5*Assumptions!D6 -> 16059.984 | E6: =E5*Assumptions!E6 -> 17862.636 | F6: =F5*Assumptions!F6 -> 19470.273 | G6: =G5*Assumptions!G6 -> 21125.246 | H6: =H5*Assumptions!H6 -> 22815.266
A7: Less: D&A | B7: =Assumptions!B8 -> 980 | C7: =Assumptions!C8 -> 1020 | D7: =Assumptions!D8 -> 1080 | E7: =Assumptions!E8 -> 1140 | F7: =Assumptions!F8 -> 1200 | G7: =Assumptions!G8 -> 1260 | H7: =Assumptions!H8 -> 1320
A8: EBIT | B8: =B6-B7 -> 12395.42 | C8: =C6-C7 -> 13546.879 | D8: =D6-D7 -> 14979.984 | E8: =E6-E7 -> 16722.636 | F8: =F6-F7 -> 18270.273 | G8: =G6-G7 -> 19865.246 | H8: =H6-H7 -> 21495.266
A9: Less: Interest Expense | B9: =Assumptions!B21 -> 90 | C9: =Assumptions!C21 -> 97.5 | D9: =Assumptions!D21 -> 97.5 | E9: =Assumptions!E21 -> 97.5 | F9: =Assumptions!F21 -> 97.5 | G9: =Assumptions!G21 -> 97.5 | H9: =Assumptions!H21 -> 97.5
A10: EBT (Profit Before Tax) | B10: =B8-B9 -> 12305.42 | C10: =C8-C9 -> 13449.379 | D10: =D8-D9 -> 14882.484 | E10: =E8-E9 -> 16625.136 | F10: =F8-F9 -> 18172.773 | G10: =G8-G9 -> 19767.746 | H10: =H8-H9 -> 21397.766
A11: Less: Tax | B11: =B10*Assumptions!B7 -> 3137.8821 | C11: =C10*Assumptions!C7 -> 3402.6929 | D11: =D10*Assumptions!D7 -> 3750.386 | E11: =E10*Assumptions!E7 -> 4189.5342 | F11: =F10*Assumptions!F7 -> 4579.5387 | G11: =G10*Assumptions!G7 -> 4981.472 | H11: =H10*Assumptions!H7 -> 5392.2369
A12: Net Income | B12: =B10-B11 -> 9167.5379 | C12: =C10-C11 -> 10046.686 | D12: =D10-D11 -> 11132.098 | E12: =E10-E11 -> 12435.601 | F12: =F10-F11 -> 13593.234 | G12: =G10-G11 -> 14786.274 | H12: =H10-H11 -> 16005.529
A14: Check: EBITDA Margin % | B14: =B6/B5 -> 0.23 | C14: =C6/C5 -> 0.24 | D14: =D6/D5 -> 0.245 | E14: =E6/E5 -> 0.25 | F14: =F6/F5 -> 0.25 | G14: =G6/G5 -> 0.25 | H14: =H6/H5 -> 0.25
A15: Check: Net Margin % | B15: =B12/B5 -> 0.15764243 | C15: =C12/C5 -> 0.16552651 | D15: =D12/D5 -> 0.16982358 | E15: =E12/E5 -> 0.17404488 | F15: =F12/F5 -> 0.17453831 | G15: =G12/G5 -> 0.17498345 | H15: =H12/H5 -> 0.17538179

Sheet Balance Sheet
A1: BALANCE SHEET
A2: HINDUSTAN UNILEVER LIMITED (₹ in Crores)
A4: Line Item | B4: FY2023 | C4: FY2024 | D4: FY2025E | E4: FY2026E | F4: FY2027E | G4: FY2028E | H4: FY2029E | I4: Formula / Source
A5: ASSETS
A6: Cash & Cash Equivalents | B6: 3500 | C6: ='Cash Flow'!C24 -> 4404.3616 | D6: ='Cash Flow'!D24 -> 5546.838 | E6: ='Cash Flow'!E24 -> 7170.1935 | F6: ='Cash Flow'!F24 -> 8791.8229 | G6: ='Cash Flow'!G24 -> 10380.667 | H6: ='Cash Flow'!H24 -> 11897.552 | I6: FY2023 anchor (hardcoded). FY24 onward links to Cash Flow Statement closing cash.
A7: Accounts Receivable | B7: ='Income Statement'!B5/365*Assumptions!B12 -> 2389.8904 | C7: ='Income Statement'!C5/365*Assumptions!C12 -> 2494.3286 | D7: ='Income Statement'!D5/365*Assumptions!D12 -> 2693.8749 | E7: ='Income Statement'!E5/365*Assumptions!E12 -> 2740.5687 | F7: ='Income Statement'!F5/365*Assumptions!F12 -> 2987.2199 | G7: ='Income Statement'!G5/365*Assumptions!G12 -> 3241.1336 | H7: ='Income Statement'!H5/365*Assumptions!H12 -> 3500.4243
A8: Inventory | B8: =('Income Statement'!B5*(1-Assumptions!B6))/365*Assumptions!B13 -> 7360.8625 | C8: =('Income Statement'!C5*(1-Assumptions!C6))/365*Assumptions!C13 -> 7330.0004 | D8: =('Income Statement'!D5*(1-Assumptions!D6))/365*Assumptions!D13 -> 7864.3188 | E8: =('Income Statement'!E5*(1-Assumptions!E6))/365*Assumptions!E13 -> 8368.5224 | F8: =('Income Statement'!F5*(1-Assumptions!F6))/365*Assumptions!F13 -> 8961.6598 | G8: =('Income Statement'!G5*(1-Assumptions!G6))/365*Assumptions!G13 -> 9549.7687 | H8: =('Income Statement'!H5*(1-Assumptions!H6))/365*Assumptions!H13 -> 10313.75
A9: Fixed Assets (Net) | B9: 10500 | C9: =B9+Assumptions!C9-Assumptions!C8 -> 10660 | D9: =C9+Assumptions!D9-Assumptions!D8 -> 10880 | E9: =D9+Assumptions!E9-Assumptions!E8 -> 11140 | F9: =E9+Assumptions!F9-Assumptions!F8 -> 11440 | G9: =F9+Assumptions!G9-Assumptions!G8 -> 11780 | H9: =G9+Assumptions!H9-Assumptions!H8 -> 12160
A10: Total Assets | B10: =SUM(B6:B9) -> 23750.753 | C10: =SUM(C6:C9) -> 24888.691 | D10: =SUM(D6:D9) -> 26985.032 | E10: =SUM(E6:E9) -> 29419.285 | F10: =SUM(F6:F9) -> 32180.703 | G10: =SUM(G6:G9) -> 34951.569 | H10: =SUM(H6:H9) -> 37871.727
A12: LIABILITIES & EQUITY
A13: Accounts Payable | B13: =('Income Statement'!B5*(1-Assumptions!B6))/365*Assumptions!B14 -> 11041.294 | C13: =('Income Statement'!C5*(1-Assumptions!C6))/365*Assumptions!C14 -> 11626.897 | D13: =('Income Statement'!D5*(1-Assumptions!D6))/365*Assumptions!D14 -> 12610.028 | E13: =('Income Statement'!E5*(1-Assumptions!E6))/365*Assumptions!E14 -> 13800.721 | F13: =('Income Statement'!F5*(1-Assumptions!F6))/365*Assumptions!F14 -> 15202.816 | G13: =('Income Statement'!G5*(1-Assumptions!G6))/365*Assumptions!G14 -> 16495.055 | H13: =('Income Statement'!H5*(1-Assumptions!H6))/365*Assumptions!H14 -> 17814.659
A14: Borrowings | B14: =Assumptions!B19 -> 2200 | C14: =Assumptions!C19 -> 2250 | D14: =Assumptions!D19 -> 2250 | E14: =Assumptions!E19 -> 2250 | F14: =Assumptions!F19 -> 2250 | G14: =Assumptions!G19 -> 2250 | H14: =Assumptions!H19 -> 2250
A15: Share Capital | B15: 235 | C15: =B15 -> 235 | D15: =C15 -> 235 | E15: =D15 -> 235 | F15: =E15 -> 235 | G15: =F15 -> 235 | H15: =G15 -> 235
A16: Retained Earnings | B16: 10274.459 | C16: =B16+'Income Statement'!C12-'Income Statement'!C12*Assumptions!C24 -> 10776.793 | D16: =C16+'Income Statement'!D12-'Income Statement'!D12*Assumptions!D24 -> 11890.003 | E16: =D16+'Income Statement'!E12-'Income Statement'!E12*Assumptions!E24 -> 13133.563 | F16: =E16+'Income Statement'!F12-'Income Statement'!F12*Assumptions!F24 -> 14492.887 | G16: =F16+'Income Statement'!G12-'Income Statement'!G12*Assumptions!G24 -> 15971.514 | H16: =G16+'Income Statement'!H12-'Income Statement'!H12*Assumptions!H24 -> 17572.067
A17: Total Liabilities & Equity | B17: =SUM(B13:B16) -> 23750.753 | C17: =SUM(C13:C16) -> 24888.691 | D17: =SUM(D13:D16) -> 26985.032 | E17: =SUM(E13:E16) -> 29419.285 | F17: =SUM(F13:F16) -> 32180.703 | G17: =SUM(G13:G16) -> 34951.569 | H17: =SUM(H13:H16) -> 37871.727
A19: Check: Assets - (Liab + Equity) | B19: =B10-B17 -> 0 | C19: =C10-C17 -> 0 | D19: =D10-D17 -> 0 | E19: =E10-E17 -> 0 | F19: =F10-F17 -> 0 | G19: =G10-G17 -> 0 | H19: =H10-H17 -> 0 | I19: Must equal zero in every column. If not, trace the break via Cash Flow Statement.

Sheet Cash Flow
A1: CASH FLOW STATEMENT
A2: HINDUSTAN UNILEVER LIMITED (₹ in Crores)
A4: Line Item | B4: FY2023 | C4: FY2024 | D4: FY2025E | E4: FY2026E | F4: FY2027E | G4: FY2028E | H4: FY2029E | I4: Formula / Source
A5: Operating Activities
A6: Net Income | B6: ='Income Statement'!B12 -> 9167.5379 | C6: ='Income Statement'!C12 -> 10046.686 | D6: ='Income Statement'!D12 -> 11132.098 | E6: ='Income Statement'!E12 -> 12435.601 | F6: ='Income Statement'!F12 -> 13593.234 | G6: ='Income Statement'!G12 -> 14786.274 | H6: ='Income Statement'!H12 -> 16005.529
A7: Add: D&A | B7: =Assumptions!B8 -> 980 | C7: =Assumptions!C8 -> 1020 | D7: =Assumptions!D8 -> 1080 | E7: =Assumptions!E8 -> 1140 | F7: =Assumptions!F8 -> 1200 | G7: =Assumptions!G8 -> 1260 | H7: =Assumptions!H8 -> 1320
A8: (Increase)/Decrease in Receivables | B8: 0 | C8: =-('Balance Sheet'!C7-'Balance Sheet'!B7) -> -104.43821 | D8: =-('Balance Sheet'!D7-'Balance Sheet'!C7) -> -199.54629 | E8: =-('Balance Sheet'!E7-'Balance Sheet'!D7) -> -46.693832 | F8: =-('Balance Sheet'!F7-'Balance Sheet'!E7) -> -246.65119 | G8: =-('Balance Sheet'!G7-'Balance Sheet'!F7) -> -253.91369 | H8: =-('Balance Sheet'!H7-'Balance Sheet'!G7) -> -259.29069
A9: (Increase)/Decrease in Inventory | B9: 0 | C9: =-('Balance Sheet'!C8-'Balance Sheet'!B8) -> 30.862089 | D9: =-('Balance Sheet'!D8-'Balance Sheet'!C8) -> -534.31845 | E9: =-('Balance Sheet'!E8-'Balance Sheet'!D8) -> -504.20359 | F9: =-('Balance Sheet'!F8-'Balance Sheet'!E8) -> -593.13738 | G9: =-('Balance Sheet'!G8-'Balance Sheet'!F8) -> -588.10892 | H9: =-('Balance Sheet'!H8-'Balance Sheet'!G8) -> -763.9815
A10: Increase/(Decrease) in Payables | B10: 0 | C10: ='Balance Sheet'!C13-'Balance Sheet'!B13 -> 585.60345 | D10: ='Balance Sheet'!D13-'Balance Sheet'!C13 -> 983.13131 | E10: ='Balance Sheet'!E13-'Balance Sheet'!D13 -> 1190.6927 | F10: ='Balance Sheet'!F13-'Balance Sheet'!E13 -> 1402.0945 | G10: ='Balance Sheet'!G13-'Balance Sheet'!F13 -> 1292.2393 | H10: ='Balance Sheet'!H13-'Balance Sheet'!G13 -> 1319.6044
A11: Cash Flow from Operations (CFO) | B11: =SUM(B6:B10) -> 10147.538 | C11: =SUM(C6:C10) -> 11578.714 | D11: =SUM(D6:D10) -> 12461.365 | E11: =SUM(E6:E10) -> 14215.397 | F11: =SUM(F6:F10) -> 15355.54 | G11: =SUM(G6:G10) -> 16496.491 | H11: =SUM(H6:H10) -> 17621.861
A13: Investing Activities
A14: Capex | B14: =-Assumptions!B9 -> -1100 | C14: =-Assumptions!C9 -> -1180 | D14: =-Assumptions!D9 -> -1300 | E14: =-Assumptions!E9 -> -1400 | F14: =-Assumptions!F9 -> -1500 | G14: =-Assumptions!G9 -> -1600 | H14: =-Assumptions!H9 -> -1700
A15: Cash Flow from Investing (CFI) | B15: =B14 -> -1100 | C15: =C14 -> -1180 | D15: =D14 -> -1300 | E15: =E14 -> -1400 | F15: =F14 -> -1500 | G15: =G14 -> -1600 | H15: =H14 -> -1700
A17: Financing Activities
A18: Change in Borrowings | B18: =Assumptions!B18 -> 0 | C18: =Assumptions!C18 -> 50 | D18: =Assumptions!D18 -> 0 | E18: =Assumptions!E18 -> 0 | F18: =Assumptions!F18 -> 0 | G18: =Assumptions!G18 -> 0 | H18: =Assumptions!H18 -> 0
A19: Dividends Paid | B19: =-('Income Statement'!B12*Assumptions!B24) -> -8709.161 | C19: =-('Income Statement'!C12*Assumptions!C24) -> -9544.3519 | D19: =-('Income Statement'!D12*Assumptions!D24) -> -10018.888 | E19: =-('Income Statement'!E12*Assumptions!E24) -> -11192.041 | F19: =-('Income Statement'!F12*Assumptions!F24) -> -12233.911 | G19: =-('Income Statement'!G12*Assumptions!G24) -> -13307.647 | H19: =-('Income Statement'!H12*Assumptions!H24) -> -14404.976
A20: Cash Flow from Financing (CFF) | B20: =SUM(B18:B19) -> -8709.161 | C20: =SUM(C18:C19) -> -9494.3519 | D20: =SUM(D18:D19) -> -10018.888 | E20: =SUM(E18:E19) -> -11192.041 | F20: =SUM(F18:F19) -> -12233.911 | G20: =SUM(G18:G19) -> -13307.647 | H20: =SUM(H18:H19) -> -14404.976
A22: Net Change in Cash | B22: n/a (anchor year) | C22: =C11+C15+C20 -> 904.36164 | D22: =D11+D15+D20 -> 1142.4764 | E22: =E11+E15+E20 -> 1623.3554 | F22: =F11+F15+F20 -> 1621.6294 | G22: =G11+G15+G20 -> 1588.8441 | H22: =H11+H15+H20 -> 1516.8851
A23: Opening Cash | B23: n/a (anchor year) | C23: ='Balance Sheet'!B6 -> 3500 | D23: =C24 -> 4404.3616 | E23: =D24 -> 5546.838 | F23: =E24 -> 7170.1935 | G23: =F24 -> 8791.8229 | H23: =G24 -> 10380.667
A24: Closing Cash | B24: ='Balance Sheet'!B6 -> 3500 | C24: =C23+C22 -> 4404.3616 | D24: =D23+D22 -> 5546.838 | E24: =E23+E22 -> 7170.1935 | F24: =F23+F22 -> 8791.8229 | G24: =G23+G22 -> 10380.667 | H24: =H23+H22 -> 11897.552
A26: Check: Closing Cash - Balance Sheet Cash | B26: =B24-'Balance Sheet'!B6 -> 0 | C26: =C24-'Balance Sheet'!C6 -> 0 | D26: =D24-'Balance Sheet'!D6 -> 0 | E26: =E24-'Balance Sheet'!E6 -> 0 | F26: =F24-'Balance Sheet'!F6 -> 0 | G26: =G24-'Balance Sheet'!G6 -> 0 | H26: =H24-'Balance Sheet'!H6 -> 0 | I26: Must equal zero in every column.

Sheet Discounted Cash Flow
A1: DISCOUNTED CASH FLOW (DCF)
A2: HINDUSTAN UNILEVER LIMITED — FCFF Approach, 5-Year Explicit Forecast
A4: DCF Assumptions
A5: WACC (Discount Rate) | B5: 0.105 | C5: Cost of equity (CAPM, Rf=7%, ERP=6%, beta=0.6) blended with low-cost debt; HUL is largely equity-funded
A6: Terminal Growth Rate | B6: 0.05 | C6: Long-run nominal GDP-linked growth assumption for India FMCG
A7: Projection Years | B7: 5
A8: Shares Outstanding (Cr) | B8: 235
A9: Current Market Price (₹) | B9: 2450 | C9: Verify against live market price before using
A10: Net Debt / (Net Cash) (₹ Cr) | B10: ='Balance Sheet'!C14-'Balance Sheet'!C6 -> -2154.3616 | C10: Formula: Latest Borrowings - Latest Cash (FY2024). Negative = net cash position.
A12: Free Cash Flow to Firm (FCFF) Build
A13: Driver | B13: FY2025E | C13: FY2026E | D13: FY2027E | E13: FY2028E | F13: FY2029E | G13: Formula
A14: Revenue | B14: ='Income Statement'!D5 -> 65550.956 | C14: ='Income Statement'!E5 -> 71450.542 | D14: ='Income Statement'!F5 -> 77881.091 | E14: ='Income Statement'!G5 -> 84500.984 | F14: ='Income Statement'!H5 -> 91261.062
A15: EBITDA | B15: ='Income Statement'!D6 -> 16059.984 | C15: ='Income Statement'!E6 -> 17862.636 | D15: ='Income Statement'!F6 -> 19470.273 | E15: ='Income Statement'!G6 -> 21125.246 | F15: ='Income Statement'!H6 -> 22815.266
A16: Less: D&A | B16: ='Income Statement'!D7 -> 1080 | C16: ='Income Statement'!E7 -> 1140 | D16: ='Income Statement'!F7 -> 1200 | E16: ='Income Statement'!G7 -> 1260 | F16: ='Income Statement'!H7 -> 1320
A17: EBIT | B17: =B15-B16 -> 14979.984 | C17: =C15-C16 -> 16722.636 | D17: =D15-D16 -> 18270.273 | E17: =E15-E16 -> 19865.246 | F17: =F15-F16 -> 21495.266
A18: Less: Tax on EBIT (unlevered) | B18: =B17*Assumptions!D7 -> 3774.956 | C18: =C17*Assumptions!E7 -> 4214.1042 | D18: =D17*Assumptions!F7 -> 4604.1087 | E18: =E17*Assumptions!G7 -> 5006.042 | F18: =F17*Assumptions!H7 -> 5416.8069
A19: NOPAT (EBIT - Tax on EBIT) | B19: =B17-B18 -> 11205.028 | C19: =C17-C18 -> 12508.531 | D19: =D17-D18 -> 13666.164 | E19: =E17-E18 -> 14859.204 | F19: =F17-F18 -> 16078.459
A20: Plus: D&A | B20: =B16 -> 1080 | C20: =C16 -> 1140 | D20: =D16 -> 1200 | E20: =E16 -> 1260 | F20: =F16 -> 1320
A21: Less: Capex | B21: =-Assumptions!D9 -> -1300 | C21: =-Assumptions!E9 -> -1400 | D21: =-Assumptions!F9 -> -1500 | E21: =-Assumptions!G9 -> -1600 | F21: =-Assumptions!H9 -> -1700
A22: Less: Increase in Net Working Capital | B22: =-((('Balance Sheet'!D7+'Balance Sheet'!D8-'Balance Sheet'!D13)-('Balance Sheet'!C7+'Balance Sheet'!C8-'Balance Sheet'!C13))) -> 249.26657 | C22: =-((('Balance Sheet'!E7+'Balance Sheet'!E8-'Balance Sheet'!E13)-('Balance Sheet'!D7+'Balance Sheet'!D8-'Balance Sheet'!D13))) -> 639.79529 | D22: =-((('Balance Sheet'!F7+'Balance Sheet'!F8-'Balance Sheet'!F13)-('Balance Sheet'!E7+'Balance Sheet'!E8-'Balance Sheet'!E13))) -> 562.30598 | E22: =-((('Balance Sheet'!G7+'Balance Sheet'!G8-'Balance Sheet'!G13)-('Balance Sheet'!F7+'Balance Sheet'!F8-'Balance Sheet'!F13))) -> 450.21672 | F22: =-((('Balance Sheet'!H7+'Balance Sheet'!H8-'Balance Sheet'!H13)-('Balance Sheet'!G7+'Balance Sheet'!G8-'Balance Sheet'!G13))) -> 296.33222 | G22: Formula: -(Change in [AR+Inventory-AP]); NWC increase is a cash outflow
A23: Free Cash Flow to Firm (FCFF) | B23: =B19+B20+B21+B22 -> 11234.295 | C23: =C19+C20+C21+C22 -> 12888.327 | D23: =D19+D20+D21+D22 -> 13928.47 | E23: =E19+E20+E21+E22 -> 14969.421 | F23: =F19+F20+F21+F22 -> 15994.791 | G23: Formula: NOPAT + D&A - Capex - Increase in NWC
A25: Year Number | B25: 1 | C25: 2 | D25: 3 | E25: 4 | F25: 5
A26: Discount Factor | B26: =1/(1+$B$5)^B25 -> 0.90497738 | C26: =1/(1+$B$5)^C25 -> 0.81898405 | D26: =1/(1+$B$5)^D25 -> 0.74116204 | E26: =1/(1+$B$5)^E25 -> 0.67073487 | F26: =1/(1+$B$5)^F25 -> 0.60699989
A27: Discounted FCFF | B27: =B23*B26 -> 10166.783 | C27: =C23*C26 -> 10555.334 | D27: =D23*D26 -> 10323.253 | E27: =E23*E26 -> 10040.513 | F27: =F23*F26 -> 9708.8363
A29: Terminal Value & Valuation
A30: Terminal Value (at end of Year 5) | B30: =F23*(1+B6)/(B5-B6) -> 305355.1 | C30: Formula: FCFF Year5 x (1+g) / (WACC - g) — Gordon Growth
A31: Discounted Terminal Value | B31: =B30*F26 -> 185350.51
A33: Sum of Discounted FCFF (Yr 1-5) | B33: =SUM(B27:F27) -> 50794.719
A34: Plus: Discounted Terminal Value | B34: =B31 -> 185350.51
A35: Enterprise Value | B35: =B33+B31 -> 236145.23
A36: Less: Net Debt / Add: Net Cash | B36: =-B10 -> 2154.3616
A37: Equity Value | B37: =B35-B10 -> 238299.59
A38: Shares Outstanding (Cr) | B38: =B8 -> 235
A40: Intrinsic Value per Share (₹) | B40: =B37/B8 -> 1014.0408
A41: Current Market Price (₹) | B41: =B9 -> 2450
A42: Upside / (Downside) | B42: =B40/B9-1 -> -0.58610579

Sheet Sensitivity
A1: SENSITIVITY ANALYSIS
A2: Intrinsic Value per Share (₹) — WACC vs Terminal Growth Rate
B4: WACC → | C4: 0.085 | D4: 0.095 | E4: 0.105 | F4: 0.115 | G4: 0.125
A5: Terminal Growth ↓ | B5: 0.03 | C5: =(SUMPRODUCT('Discounted Cash Flow'!$B$23:$F$23,1/(1+C$4)^{1,2,3,4,5})+(INDEX('Discounted Cash Flow'!$B$23:$F$23,1,5)*(1+$B5)/(C$4-$B5))/(1+C$4)^5-'Discounted Cash Flow'!$B$10)/'Discounted Cash Flow'!$B$8 -> 1085.1364 | D5: =(SUMPRODUCT('Discounted Cash Flow'!$B$23:$F$23,1/(1+D$4)^{1,2,3,4,5})+(INDEX('Discounted Cash Flow'!$B$23:$F$23,1,5)*(1+$B5)/(D$4-$B5))/(1+D$4)^5-'Discounted Cash Flow'!$B$10)/'Discounted Cash Flow'!$B$8 -> 916.36834 | E5: =(SUMPRODUCT('Discounted Cash Flow'!$B$23:$F$23,1/(1+E$4)^{1,2,3,4,5})+(INDEX('Discounted Cash Flow'!$B$23:$F$23,1,5)*(1+$B5)/(E$4-$B5))/(1+E$4)^5-'Discounted Cash Flow'!$B$10)/'Discounted Cash Flow'!$B$8 -> 792.69687 | F5: =(SUMPRODUCT('Discounted Cash Flow'!$B$23:$F$23,1/(1+F$4)^{1,2,3,4,5})+(INDEX('Discounted Cash Flow'!$B$23:$F$23,1,5)*(1+$B5)/(F$4-$B5))/(1+F$4)^5-'Discounted Cash Flow'!$B$10)/'Discounted Cash Flow'!$B$8 -> 698.20195 | G5: =(SUMPRODUCT('Discounted Cash Flow'!$B$23:$F$23,1/(1+G$4)^{1,2,3,4,5})+(INDEX('Discounted Cash Flow'!$B$23:$F$23,1,5)*(1+$B5)/(G$4-$B5))/(1+G$4)^5-'Discounted Cash Flow'!$B$10)/'Discounted Cash Flow'!$B$8 -> 623.66689
B6: 0.04 | C6: =(SUMPRODUCT('Discounted Cash Flow'!$B$23:$F$23,1/(1+C$4)^{1,2,3,4,5})+(INDEX('Discounted Cash Flow'!$B$23:$F$23,1,5)*(1+$B6)/(C$4-$B6))/(1+C$4)^5-'Discounted Cash Flow'!$B$10)/'Discounted Cash Flow'!$B$8 -> 1283.5706 | D6: =(SUMPRODUCT('Discounted Cash Flow'!$B$23:$F$23,1/(1+D$4)^{1,2,3,4,5})+(INDEX('Discounted Cash Flow'!$B$23:$F$23,1,5)*(1+$B6)/(D$4-$B6))/(1+D$4)^5-'Discounted Cash Flow'!$B$10)/'Discounted Cash Flow'!$B$8 -> 1048.7958 | E6: =(SUMPRODUCT('Discounted Cash Flow'!$B$23:$F$23,1/(1+E$4)^{1,2,3,4,5})+(INDEX('Discounted Cash Flow'!$B$23:$F$23,1,5)*(1+$B6)/(E$4-$B6))/(1+E$4)^5-'Discounted Cash Flow'!$B$10)/'Discounted Cash Flow'!$B$8 -> 886.34238 | F6: =(SUMPRODUCT('Discounted Cash Flow'!$B$23:$F$23,1/(1+F$4)^{1,2,3,4,5})+(INDEX('Discounted Cash Flow'!$B$23:$F$23,1,5)*(1+$B6)/(F$4-$B6))/(1+F$4)^5-'Discounted Cash Flow'!$B$10)/'Discounted Cash Flow'!$B$8 -> 767.27856 | G6: =(SUMPRODUCT('Discounted Cash Flow'!$B$23:$F$23,1/(1+G$4)^{1,2,3,4,5})+(INDEX('Discounted Cash Flow'!$B$23:$F$23,1,5)*(1+$B6)/(G$4-$B6))/(1+G$4)^5-'Discounted Cash Flow'!$B$10)/'Discounted Cash Flow'!$B$8 -> 676.28776
B7: 0.05 | C7: =(SUMPRODUCT('Discounted Cash Flow'!$B$23:$F$23,1/(1+C$4)^{1,2,3,4,5})+(INDEX('Discounted Cash Flow'!$B$23:$F$23,1,5)*(1+$B7)/(C$4-$B7))/(1+C$4)^5-'Discounted Cash Flow'!$B$10)/'Discounted Cash Flow'!$B$8 -> 1595.3958 | D7: =(SUMPRODUCT('Discounted Cash Flow'!$B$23:$F$23,1/(1+D$4)^{1,2,3,4,5})+(INDEX('Discounted Cash Flow'!$B$23:$F$23,1,5)*(1+$B7)/(D$4-$B7))/(1+D$4)^5-'Discounted Cash Flow'!$B$10)/'Discounted Cash Flow'!$B$8 -> 1240.08 | E7: =(SUMPRODUCT('Discounted Cash Flow'!$B$23:$F$23,1/(1+E$4)^{1,2,3,4,5})+(INDEX('Discounted Cash Flow'!$B$23:$F$23,1,5)*(1+$B7)/(E$4-$B7))/(1+E$4)^5-'Discounted Cash Flow'!$B$10)/'Discounted Cash Flow'!$B$8 -> 1014.0408 | F7: =(SUMPRODUCT('Discounted Cash Flow'!$B$23:$F$23,1/(1+F$4)^{1,2,3,4,5})+(INDEX('Discounted Cash Flow'!$B$23:$F$23,1,5)*(1+$B7)/(F$4-$B7))/(1+F$4)^5-'Discounted Cash Flow'!$B$10)/'Discounted Cash Flow'!$B$8 -> 857.60952 | G7: =(SUMPRODUCT('Discounted Cash Flow'!$B$23:$F$23,1/(1+G$4)^{1,2,3,4,5})+(INDEX('Discounted Cash Flow'!$B$23:$F$23,1,5)*(1+$B7)/(G$4-$B7))/(1+G$4)^5-'Discounted Cash Flow'!$B$10)/'Discounted Cash Flow'!$B$8 -> 742.94087
B8: 0.06 | C8: =(SUMPRODUCT('Discounted Cash Flow'!$B$23:$F$23,1/(1+C$4)^{1,2,3,4,5})+(INDEX('Discounted Cash Flow'!$B$23:$F$23,1,5)*(1+$B8)/(C$4-$B8))/(1+C$4)^5-'Discounted Cash Flow'!$B$10)/'Discounted Cash Flow'!$B$8 -> 2156.6811 | D8: =(SUMPRODUCT('Discounted Cash Flow'!$B$23:$F$23,1/(1+D$4)^{1,2,3,4,5})+(INDEX('Discounted Cash Flow'!$B$23:$F$23,1,5)*(1+$B8)/(D$4-$B8))/(1+D$4)^5-'Discounted Cash Flow'!$B$10)/'Discounted Cash Flow'!$B$8 -> 1540.6694 | E8: =(SUMPRODUCT('Discounted Cash Flow'!$B$23:$F$23,1/(1+E$4)^{1,2,3,4,5})+(INDEX('Discounted Cash Flow'!$B$23:$F$23,1,5)*(1+$B8)/(E$4-$B8))/(1+E$4)^5-'Discounted Cash Flow'!$B$10)/'Discounted Cash Flow'!$B$8 -> 1198.4941 | F8: =(SUMPRODUCT('Discounted Cash Flow'!$B$23:$F$23,1/(1+F$4)^{1,2,3,4,5})+(INDEX('Discounted Cash Flow'!$B$23:$F$23,1,5)*(1+$B8)/(F$4-$B8))/(1+F$4)^5-'Discounted Cash Flow'!$B$10)/'Discounted Cash Flow'!$B$8 -> 980.7881 | G8: =(SUMPRODUCT('Discounted Cash Flow'!$B$23:$F$23,1/(1+G$4)^{1,2,3,4,5})+(INDEX('Discounted Cash Flow'!$B$23:$F$23,1,5)*(1+$B8)/(G$4-$B8))/(1+G$4)^5-'Discounted Cash Flow'!$B$10)/'Discounted Cash Flow'!$B$8 -> 830.10264
B9: 0.07 | C9: =(SUMPRODUCT('Discounted Cash Flow'!$B$23:$F$23,1/(1+C$4)^{1,2,3,4,5})+(INDEX('Discounted Cash Flow'!$B$23:$F$23,1,5)*(1+$B9)/(C$4-$B9))/(1+C$4)^5-'Discounted Cash Flow'!$B$10)/'Discounted Cash Flow'!$B$8 -> 3466.3469 | D9: =(SUMPRODUCT('Discounted Cash Flow'!$B$23:$F$23,1/(1+D$4)^{1,2,3,4,5})+(INDEX('Discounted Cash Flow'!$B$23:$F$23,1,5)*(1+$B9)/(D$4-$B9))/(1+D$4)^5-'Discounted Cash Flow'!$B$10)/'Discounted Cash Flow'!$B$8 -> 2081.7303 | E9: =(SUMPRODUCT('Discounted Cash Flow'!$B$23:$F$23,1/(1+E$4)^{1,2,3,4,5})+(INDEX('Discounted Cash Flow'!$B$23:$F$23,1,5)*(1+$B9)/(E$4-$B9))/(1+E$4)^5-'Discounted Cash Flow'!$B$10)/'Discounted Cash Flow'!$B$8 -> 1488.3493 | F9: =(SUMPRODUCT('Discounted Cash Flow'!$B$23:$F$23,1/(1+F$4)^{1,2,3,4,5})+(INDEX('Discounted Cash Flow'!$B$23:$F$23,1,5)*(1+$B9)/(F$4-$B9))/(1+F$4)^5-'Discounted Cash Flow'!$B$10)/'Discounted Cash Flow'!$B$8 -> 1158.7127 | G9: =(SUMPRODUCT('Discounted Cash Flow'!$B$23:$F$23,1/(1+G$4)^{1,2,3,4,5})+(INDEX('Discounted Cash Flow'!$B$23:$F$23,1,5)*(1+$B9)/(G$4-$B9))/(1+G$4)^5-'Discounted Cash Flow'!$B$10)/'Discounted Cash Flow'!$B$8 -> 948.95958
A12: Each cell independently recomputes Enterprise Value, Equity Value, and price per share at that WACC/terminal-growth pair, using the same FCFF projections as the DCF tab. Highlighted cell = base case.
